README.md
setup.py
xsrfprobe/__init__.py
xsrfprobe/xsrfprobe.py
xsrfprobe.egg-info/PKG-INFO
xsrfprobe.egg-info/SOURCES.txt
xsrfprobe.egg-info/dependency_links.txt
xsrfprobe.egg-info/requires.txt
xsrfprobe.egg-info/top_level.txt
xsrfprobe/bin/xsrfprobe
xsrfprobe/core/__init__.py
xsrfprobe/core/banner.py
xsrfprobe/core/colors.py
xsrfprobe/core/forms.py
xsrfprobe/core/inputin.py
xsrfprobe/core/logger.py
xsrfprobe/core/main.py
xsrfprobe/core/options.py
xsrfprobe/core/prettify.py
xsrfprobe/core/randua.py
xsrfprobe/core/request.py
xsrfprobe/core/updater.py
xsrfprobe/core/utils.py
xsrfprobe/core/verbout.py
xsrfprobe/files/__init__.py
xsrfprobe/files/config.py
xsrfprobe/files/dcodelist.py
xsrfprobe/files/discovered.py
xsrfprobe/files/paramlist.py
xsrfprobe/modules/Analysis.py
xsrfprobe/modules/Checkpost.py
xsrfprobe/modules/Cookie.py
xsrfprobe/modules/Crawler.py
xsrfprobe/modules/Debugger.py
xsrfprobe/modules/Encoding.py
xsrfprobe/modules/Entropy.py
xsrfprobe/modules/Generator.py
xsrfprobe/modules/Origin.py
xsrfprobe/modules/Parser.py
xsrfprobe/modules/Persistence.py
xsrfprobe/modules/Referer.py
xsrfprobe/modules/Tamper.py
xsrfprobe/modules/Token.py
xsrfprobe/modules/__init__.py