Metadata-Version: 2.1
Name: xsrfprobe
Version: 2.3.1
Summary: The Prime Cross Site Request Forgery (CSRF) Audit & Exploitation Toolkit
Home-page: https://github.com/0xInfection/XSRFProbe
Author: Pinaki Mondal
Author-email: theinfecteddrake@gmail.com
License: GPLv3
Download-URL: https://github.com/0xInfection/XSRFProbe/archive/v2.3.1.zip
Keywords: csrf,xsrf,appsec,vulnerability scanner,webapps,hacking
Platform: UNKNOWN
Classifier: Development Status :: 5 - Production/Stable
Classifier: Intended Audience :: System Administrators
Classifier: Intended Audience :: Developers
Classifier: Intended Audience :: Information Technology
Classifier: Operating System :: OS Independent
Classifier: Topic :: Internet
Classifier: Topic :: Security
Classifier: License :: OSI Approved :: GNU General Public License v3 (GPLv3)
Classifier: Programming Language :: Python :: 3
